st_visium_datasets/__init__.py
st_visium_datasets/base.py
st_visium_datasets/builder.py
st_visium_datasets/configs/human/brain/cytassist-11mm-ffpe-human-glioblastoma-2-0-1.json
st_visium_datasets/configs/human/brain/parent-visium-human-glioblastoma-1-2-0.json
st_visium_datasets/configs/human/brain/targeted-visium-human-glioblastoma-pan-cancer-1-2-0.json
st_visium_datasets/configs/human/brain/v1-human-brain-section-1-1-1-0.json
st_visium_datasets/configs/human/brain/v1-human-brain-section-2-1-1-0.json
st_visium_datasets/configs/human/brain-cerebellum/parent-visium-human-cerebellum-1-2-0.json
st_visium_datasets/configs/human/brain-cerebellum/targeted-visium-human-cerebellum-neuroscience-1-2-0.json
st_visium_datasets/configs/human/breast/cytassist-fresh-frozen-human-breast-cancer-2-0-1.json
st_visium_datasets/configs/human/breast/parent-visium-human-breast-cancer-1-2-0.json
st_visium_datasets/configs/human/breast/targeted-visium-human-breast-cancer-immunology-1-2-0.json
st_visium_datasets/configs/human/breast/v1-breast-cancer-block-a-section-1-1-0-0.json
st_visium_datasets/configs/human/breast/v1-breast-cancer-block-a-section-1-1-1-0.json
st_visium_datasets/configs/human/breast/v1-breast-cancer-block-a-section-2-1-0-0.json
st_visium_datasets/configs/human/breast/v1-breast-cancer-block-a-section-2-1-1-0.json
st_visium_datasets/configs/human/breast/v1-human-invasive-ductal-carcinoma-1-2-0.json
st_visium_datasets/configs/human/breast/visium-ffpe-human-breast-cancer-1-3-0.json
st_visium_datasets/configs/human/breast/visium-human-breast-cancer-1-3-0.json
st_visium_datasets/configs/human/cerebellum/targeted-visium-human-cerebellum-neuroscience-2-0-0.json
st_visium_datasets/configs/human/colon/cytassist-ffpe-human-colon-post-xenium-rep1-2-1-0.json
st_visium_datasets/configs/human/colon/cytassist-ffpe-human-colon-post-xenium-rep2-2-1-0.json
st_visium_datasets/configs/human/colon/cytassist-ffpe-human-colon-rep1-2-1-0.json
st_visium_datasets-0.3.0.dist-info/LICENSE
st_visium_datasets-0.3.0.dist-info/METADATA
st_visium_datasets-0.3.0.dist-info/WHEEL
st_visium_datasets-0.3.0.dist-info/RECORD
