Metadata-Version: 2.1
Name: st-visium-datasets
Version: 0.3.0
Summary: 
License: MIT
Author: Ouail Bendidi
Author-email: ouail.bendidi@gmail.com
Requires-Python: >=3.8,<4.0
Classifier: License :: OSI Approved :: MIT License
Classifier: Programming Language :: Python :: 3
Classifier: Programming Language :: Python :: 3.8
Classifier: Programming Language :: Python :: 3.9
Classifier: Programming Language :: Python :: 3.10
Classifier: Programming Language :: Python :: 3.11
Classifier: Programming Language :: Python :: 3.12
Requires-Dist: datasets (>=2.16.1,<3.0.0)
Requires-Dist: imagecodecs (>=2023.3.16,<2024.0.0)
Requires-Dist: pandas (>=2.0.3,<3.0.0)
Requires-Dist: pillow (>=10.1.0,<11.0.0)
Requires-Dist: pydantic (>=2,<3)
Requires-Dist: scipy (==1.10.*) ; python_version < "3.9"
Requires-Dist: scipy (>=1.11.4,<2.0.0) ; python_version >= "3.9"
Requires-Dist: tabulate (>=0.9.0,<0.10.0)
Requires-Dist: tifffile (>=2023.4.12,<2024.0.0)
